r3fit-0.1.3.dist-info/METADATA
r3fit-0.1.3.dist-info/WHEEL
r3fit/__init__.py
r3fit/r3fit.cp313-win_amd64.pyd
r3fit-0.1.3.dist-info/RECORD
